bitmex_async_rest/__init__.py
bitmex_async_rest/api.py
bitmex_async_rest/auth.py
bitmex_async_rest-0.9.0.dist-info/LICENSE
bitmex_async_rest-0.9.0.dist-info/WHEEL
bitmex_async_rest-0.9.0.dist-info/METADATA
bitmex_async_rest-0.9.0.dist-info/RECORD
