Metadata-Version: 2.1
Name: bitmex-async-rest
Version: 0.9.0
Summary: Async REST Api wrapper for BitMEX cryptocurrency derivatives exchange.
Home-page: https://github.com/andersea/bitmex-async-rest
License: MIT
Keywords: BitMEX,REST,AnyIO,asks,async
Author: Anders Ellenshøj Andersen
Author-email: andersa@ellenshoej.dk
Requires-Python: >=3.7,<4.0
Classifier: Development Status :: 4 - Beta
Classifier: Framework :: Trio
Classifier: Intended Audience :: Developers
Classifier: License :: OSI Approved :: MIT License
Classifier: Natural Language :: English
Classifier: Programming Language :: Python :: 3
Classifier: Programming Language :: Python :: 3.10
Classifier: Programming Language :: Python :: 3.7
Classifier: Programming Language :: Python :: 3.8
Classifier: Programming Language :: Python :: 3.9
Requires-Dist: anyio (>=2.0.2,<3.0.0)
Requires-Dist: asks (>=2.4.12,<3.0.0)
Requires-Dist: orjson (>=3.6.4,<4.0.0)
